{
    "flags": {},
    "imageData": null,
    "imageHeight": 1361,
    "imagePath": "/home/ancv/Work/OCR/DATASET/doanh_nghiep_final/labelme_dn1/163_IMG_20220504_150907_593.jpg",
    "imageWidth": 1024,
    "shapes": [
        {
            "flags": {},
            "label": "OTHER",
            "points": [
                [
                    551,
                    633
                ],
                [
                    553,
                    649
                ],
                [
                    420,
                    673
                ],
                [
                    419,
                    657
                ]
            ],
            "shape_type": "polygon"
        },
        {
            "flags": {},
            "label": "OTHER",
            "points": [
                [
                    602,
                    640
                ],
                [
                    604,
                    656
                ],
                [
                    421,
                    691
                ],
                [
                    421,
                    674
                ]
            ],
            "shape_type": "polygon"
        },
        {
            "flags": {},
            "label": "REPRESENTATIVE/OWNER",
            "points": [
                [
                    165,
                    338
                ],
                [
                    352,
                    344
                ],
                [
                    353,
                    359
                ],
                [
                    164,
                    350
                ]
            ],
            "shape_type": "polygon"
        },
        {
            "flags": {},
            "label": "REPRESENTATIVE/OWNER",
            "points": [
                [
                    477,
                    340
                ],
                [
                    548,
                    332
                ],
                [
                    550,
                    347
                ],
                [
                    479,
                    353
                ]
            ],
            "shape_type": "polygon"
        },
        {
            "flags": {},
            "label": "REPRESENTATIVE/OWNER",
            "points": [
                [
                    163,
                    356
                ],
                [
                    289,
                    364
                ],
                [
                    289,
                    376
                ],
                [
                    162,
                    368
                ]
            ],
            "shape_type": "polygon"
        },
        {
            "flags": {},
            "label": "REPRESENTATIVE/OWNER",
            "points": [
                [
                    321,
                    364
                ],
                [
                    403,
                    363
                ],
                [
                    405,
                    375
                ],
                [
                    320,
                    377
                ]
            ],
            "shape_type": "polygon"
        },
        {
            "flags": {},
            "label": "REPRESENTATIVE/OWNER",
            "points": [
                [
                    477,
                    358
                ],
                [
                    586,
                    346
                ],
                [
                    587,
                    358
                ],
                [
                    484,
                    370
                ]
            ],
            "shape_type": "polygon"
        },
        {
            "flags": {},
            "label": "REPRESENTATIVE/OWNER",
            "points": [
                [
                    164,
                    376
                ],
                [
                    339,
                    383
                ],
                [
                    478,
                    374
                ],
                [
                    479,
                    387
                ],
                [
                    332,
                    396
                ],
                [
                    161,
                    390
                ]
            ],
            "shape_type": "polygon"
        },
        {
            "flags": {},
            "label": "REPRESENTATIVE/OWNER",
            "points": [
                [
                    263,
                    396
                ],
                [
                    262,
                    408
                ],
                [
                    161,
                    403
                ],
                [
                    161,
                    390
                ]
            ],
            "shape_type": "polygon"
        },
        {
            "flags": {},
            "label": "REPRESENTATIVE/OWNER",
            "points": [
                [
                    160,
                    409
                ],
                [
                    288,
                    414
                ],
                [
                    287,
                    427
                ],
                [
                    161,
                    426
                ]
            ],
            "shape_type": "polygon"
        },
        {
            "flags": {},
            "label": "REPRESENTATIVE/OWNER",
            "points": [
                [
                    400,
                    409
                ],
                [
                    606,
                    384
                ],
                [
                    608,
                    399
                ],
                [
                    401,
                    423
                ]
            ],
            "shape_type": "polygon"
        },
        {
            "flags": {},
            "label": "REPRESENTATIVE/OWNER",
            "points": [
                [
                    495,
                    411
                ],
                [
                    497,
                    424
                ],
                [
                    400,
                    436
                ],
                [
                    398,
                    423
                ]
            ],
            "shape_type": "polygon"
        },
        {
            "flags": {},
            "label": "REPRESENTATIVE/OWNER",
            "points": [
                [
                    159,
                    457
                ],
                [
                    279,
                    459
                ],
                [
                    276,
                    474
                ],
                [
                    159,
                    479
                ]
            ],
            "shape_type": "polygon"
        },
        {
            "flags": {},
            "label": "REPRESENTATIVE/OWNER",
            "points": [
                [
                    203,
                    482
                ],
                [
                    608,
                    442
                ],
                [
                    613,
                    466
                ],
                [
                    206,
                    501
                ]
            ],
            "shape_type": "polygon"
        },
        {
            "flags": {},
            "label": "REPRESENTATIVE/OWNER",
            "points": [
                [
                    154,
                    504
                ],
                [
                    251,
                    503
                ],
                [
                    252,
                    518
                ],
                [
                    153,
                    521
                ]
            ],
            "shape_type": "polygon"
        },
        {
            "flags": {},
            "label": "REPRESENTATIVE/OWNER",
            "points": [
                [
                    263,
                    522
                ],
                [
                    551,
                    487
                ],
                [
                    554,
                    506
                ],
                [
                    265,
                    539
                ]
            ],
            "shape_type": "polygon"
        },
        {
            "flags": {},
            "label": "BRANCH_DETAIL",
            "points": [
                [
                    152,
                    549
                ],
                [
                    317,
                    539
                ],
                [
                    317,
                    552
                ],
                [
                    152,
                    567
                ]
            ],
            "shape_type": "polygon"
        },
        {
            "flags": {},
            "label": "BRANCH_DETAIL",
            "points": [
                [
                    258,
                    559
                ],
                [
                    525,
                    525
                ],
                [
                    526,
                    540
                ],
                [
                    318,
                    566
                ],
                [
                    259,
                    570
                ]
            ],
            "shape_type": "polygon"
        },
        {
            "flags": {},
            "label": "BRANCH_DETAIL",
            "points": [
                [
                    269,
                    572
                ],
                [
                    340,
                    566
                ],
                [
                    579,
                    531
                ],
                [
                    581,
                    547
                ],
                [
                    338,
                    579
                ],
                [
                    268,
                    585
                ]
            ],
            "shape_type": "polygon"
        },
        {
            "flags": {},
            "label": "OFFICE_DETAIL",
            "points": [
                [
                    144,
                    623
                ],
                [
                    374,
                    596
                ],
                [
                    376,
                    612
                ],
                [
                    148,
                    639
                ]
            ],
            "shape_type": "polygon"
        },
        {
            "flags": {},
            "label": "DOCUMENT",
            "points": [
                [
                    43,
                    922
                ],
                [
                    76,
                    688
                ],
                [
                    101,
                    461
                ],
                [
                    117,
                    359
                ],
                [
                    193,
                    297
                ],
                [
                    221,
                    292
                ],
                [
                    494,
                    295
                ],
                [
                    656,
                    285
                ],
                [
                    760,
                    572
                ],
                [
                    920,
                    940
                ],
                [
                    0,
                    1100
                ]
            ],
            "shape_type": "polygon"
        },
        {
            "flags": {},
            "label": "BRANCH_DETAIL",
            "points": [
                [
                    241,
                    561
                ],
                [
                    242,
                    574
                ],
                [
                    153,
                    579
                ],
                [
                    152,
                    567
                ]
            ],
            "shape_type": "polygon"
        },
        {
            "flags": {},
            "label": "BRANCH_DETAIL",
            "points": [
                [
                    262,
                    574
                ],
                [
                    262,
                    587
                ],
                [
                    151,
                    596
                ],
                [
                    151,
                    581
                ]
            ],
            "shape_type": "polygon"
        },
        {
            "flags": {},
            "label": "BRANCH_DETAIL",
            "points": [
                [
                    333,
                    580
                ],
                [
                    332,
                    594
                ],
                [
                    271,
                    600
                ],
                [
                    272,
                    587
                ]
            ],
            "shape_type": "polygon"
        },
        {
            "flags": {},
            "label": "BRANCH_DETAIL",
            "points": [
                [
                    255,
                    590
                ],
                [
                    254,
                    602
                ],
                [
                    148,
                    613
                ],
                [
                    149,
                    596
                ]
            ],
            "shape_type": "polygon"
        }
    ],
    "version": "5.0.1"
}