{
    "flags": {},
    "imageData": null,
    "imageHeight": 1361,
    "imagePath": "/home/ancv/Work/OCR/DATASET/doanh_nghiep_final/labelme_dn1/188_IMG_20220504_142045_472.jpg",
    "imageWidth": 1024,
    "shapes": [
        {
            "flags": {},
            "label": "SHAREHOLDER",
            "points": [
                [
                    837,
                    807
                ],
                [
                    775,
                    803
                ],
                [
                    773,
                    786
                ],
                [
                    837,
                    791
                ]
            ],
            "shape_type": "polygon"
        },
        {
            "flags": {},
            "label": "SHAREHOLDER",
            "points": [
                [
                    756,
                    799
                ],
                [
                    745,
                    797
                ],
                [
                    744,
                    784
                ],
                [
                    757,
                    785
                ]
            ],
            "shape_type": "polygon"
        },
        {
            "flags": {},
            "label": "SHAREHOLDER",
            "points": [
                [
                    831,
                    701
                ],
                [
                    779,
                    694
                ],
                [
                    779,
                    682
                ],
                [
                    834,
                    686
                ]
            ],
            "shape_type": "polygon"
        },
        {
            "flags": {},
            "label": "SHAREHOLDER",
            "points": [
                [
                    846,
                    604
                ],
                [
                    780,
                    601
                ],
                [
                    779,
                    588
                ],
                [
                    846,
                    592
                ]
            ],
            "shape_type": "polygon"
        },
        {
            "flags": {},
            "label": "SHAREHOLDER",
            "points": [
                [
                    772,
                    602
                ],
                [
                    753,
                    600
                ],
                [
                    753,
                    585
                ],
                [
                    770,
                    586
                ]
            ],
            "shape_type": "polygon"
        },
        {
            "flags": {},
            "label": "SHAREHOLDER",
            "points": [
                [
                    758,
                    694
                ],
                [
                    748,
                    693
                ],
                [
                    748,
                    681
                ],
                [
                    761,
                    682
                ]
            ],
            "shape_type": "polygon"
        },
        {
            "flags": {},
            "label": "SHAREHOLDER",
            "points": [
                [
                    828,
                    541
                ],
                [
                    782,
                    537
                ],
                [
                    782,
                    522
                ],
                [
                    830,
                    526
                ]
            ],
            "shape_type": "polygon"
        },
        {
            "flags": {},
            "label": "SHAREHOLDER",
            "points": [
                [
                    768,
                    535
                ],
                [
                    755,
                    533
                ],
                [
                    758,
                    522
                ],
                [
                    768,
                    525
                ]
            ],
            "shape_type": "polygon"
        },
        {
            "flags": {},
            "label": "SHAREHOLDER",
            "points": [
                [
                    772,
                    473
                ],
                [
                    758,
                    471
                ],
                [
                    758,
                    461
                ],
                [
                    775,
                    461
                ]
            ],
            "shape_type": "polygon"
        },
        {
            "flags": {},
            "label": "SHAREHOLDER",
            "points": [
                [
                    821,
                    476
                ],
                [
                    784,
                    474
                ],
                [
                    782,
                    461
                ],
                [
                    819,
                    461
                ]
            ],
            "shape_type": "polygon"
        },
        {
            "flags": {},
            "label": "SHAREHOLDER",
            "points": [
                [
                    828,
                    391
                ],
                [
                    788,
                    391
                ],
                [
                    789,
                    377
                ],
                [
                    828,
                    378
                ]
            ],
            "shape_type": "polygon"
        },
        {
            "flags": {},
            "label": "SHAREHOLDER",
            "points": [
                [
                    774,
                    391
                ],
                [
                    762,
                    387
                ],
                [
                    763,
                    376
                ],
                [
                    775,
                    376
                ]
            ],
            "shape_type": "polygon"
        },
        {
            "flags": {},
            "label": "SHAREHOLDER",
            "points": [
                [
                    724,
                    794
                ],
                [
                    661,
                    794
                ],
                [
                    660,
                    778
                ],
                [
                    723,
                    782
                ]
            ],
            "shape_type": "polygon"
        },
        {
            "flags": {},
            "label": "SHAREHOLDER",
            "points": [
                [
                    709,
                    690
                ],
                [
                    667,
                    690
                ],
                [
                    665,
                    674
                ],
                [
                    706,
                    676
                ]
            ],
            "shape_type": "polygon"
        },
        {
            "flags": {},
            "label": "SHAREHOLDER",
            "points": [
                [
                    712,
                    595
                ],
                [
                    674,
                    593
                ],
                [
                    675,
                    580
                ],
                [
                    713,
                    581
                ]
            ],
            "shape_type": "polygon"
        },
        {
            "flags": {},
            "label": "SHAREHOLDER",
            "points": [
                [
                    729,
                    530
                ],
                [
                    677,
                    530
                ],
                [
                    680,
                    515
                ],
                [
                    731,
                    519
                ]
            ],
            "shape_type": "polygon"
        },
        {
            "flags": {},
            "label": "SHAREHOLDER",
            "points": [
                [
                    754,
                    472
                ],
                [
                    683,
                    469
                ],
                [
                    683,
                    454
                ],
                [
                    754,
                    459
                ]
            ],
            "shape_type": "polygon"
        },
        {
            "flags": {},
            "label": "SHAREHOLDER",
            "points": [
                [
                    733,
                    387
                ],
                [
                    689,
                    386
                ],
                [
                    690,
                    374
                ],
                [
                    732,
                    376
                ]
            ],
            "shape_type": "polygon"
        },
        {
            "flags": {},
            "label": "SHAREHOLDER",
            "points": [
                [
                    554,
                    784
                ],
                [
                    500,
                    780
                ],
                [
                    501,
                    763
                ],
                [
                    555,
                    768
                ]
            ],
            "shape_type": "polygon"
        },
        {
            "flags": {},
            "label": "SHAREHOLDER",
            "points": [
                [
                    464,
                    792
                ],
                [
                    408,
                    788
                ],
                [
                    409,
                    774
                ],
                [
                    465,
                    776
                ]
            ],
            "shape_type": "polygon"
        },
        {
            "flags": {},
            "label": "SHAREHOLDER",
            "points": [
                [
                    492,
                    778
                ],
                [
                    406,
                    773
                ],
                [
                    409,
                    757
                ],
                [
                    493,
                    762
                ]
            ],
            "shape_type": "polygon"
        },
        {
            "flags": {},
            "label": "SHAREHOLDER",
            "points": [
                [
                    486,
                    688
                ],
                [
                    424,
                    685
                ],
                [
                    425,
                    672
                ],
                [
                    491,
                    675
                ]
            ],
            "shape_type": "polygon"
        },
        {
            "flags": {},
            "label": "SHAREHOLDER",
            "points": [
                [
                    462,
                    702
                ],
                [
                    419,
                    701
                ],
                [
                    418,
                    686
                ],
                [
                    465,
                    689
                ]
            ],
            "shape_type": "polygon"
        },
        {
            "flags": {},
            "label": "SHAREHOLDER",
            "points": [
                [
                    455,
                    673
                ],
                [
                    423,
                    671
                ],
                [
                    423,
                    655
                ],
                [
                    455,
                    658
                ]
            ],
            "shape_type": "polygon"
        },
        {
            "flags": {},
            "label": "SHAREHOLDER",
            "points": [
                [
                    406,
                    670
                ],
                [
                    393,
                    669
                ],
                [
                    393,
                    658
                ],
                [
                    394,
                    657
                ],
                [
                    411,
                    655
                ]
            ],
            "shape_type": "polygon"
        },
        {
            "flags": {},
            "label": "SHAREHOLDER",
            "points": [
                [
                    387,
                    770
                ],
                [
                    375,
                    769
                ],
                [
                    374,
                    759
                ],
                [
                    376,
                    755
                ],
                [
                    390,
                    755
                ]
            ],
            "shape_type": "polygon"
        },
        {
            "flags": {},
            "label": "SHAREHOLDER",
            "points": [
                [
                    422,
                    575
                ],
                [
                    411,
                    575
                ],
                [
                    413,
                    562
                ],
                [
                    427,
                    561
                ]
            ],
            "shape_type": "polygon"
        },
        {
            "flags": {},
            "label": "SHAREHOLDER",
            "points": [
                [
                    492,
                    579
                ],
                [
                    444,
                    577
                ],
                [
                    444,
                    562
                ],
                [
                    493,
                    565
                ]
            ],
            "shape_type": "polygon"
        },
        {
            "flags": {},
            "label": "SHAREHOLDER",
            "points": [
                [
                    527,
                    516
                ],
                [
                    454,
                    510
                ],
                [
                    453,
                    498
                ],
                [
                    530,
                    504
                ]
            ],
            "shape_type": "polygon"
        },
        {
            "flags": {},
            "label": "SHAREHOLDER",
            "points": [
                [
                    477,
                    526
                ],
                [
                    451,
                    522
                ],
                [
                    454,
                    512
                ],
                [
                    480,
                    513
                ]
            ],
            "shape_type": "polygon"
        },
        {
            "flags": {},
            "label": "SHAREHOLDER",
            "points": [
                [
                    437,
                    511
                ],
                [
                    423,
                    508
                ],
                [
                    424,
                    499
                ],
                [
                    436,
                    498
                ]
            ],
            "shape_type": "polygon"
        },
        {
            "flags": {},
            "label": "SHAREHOLDER",
            "points": [
                [
                    575,
                    680
                ],
                [
                    514,
                    679
                ],
                [
                    514,
                    663
                ],
                [
                    575,
                    668
                ]
            ],
            "shape_type": "polygon"
        },
        {
            "flags": {},
            "label": "SHAREHOLDER",
            "points": [
                [
                    581,
                    585
                ],
                [
                    531,
                    582
                ],
                [
                    529,
                    568
                ],
                [
                    581,
                    573
                ]
            ],
            "shape_type": "polygon"
        },
        {
            "flags": {},
            "label": "SHAREHOLDER",
            "points": [
                [
                    591,
                    521
                ],
                [
                    537,
                    520
                ],
                [
                    538,
                    504
                ],
                [
                    589,
                    508
                ]
            ],
            "shape_type": "polygon"
        },
        {
            "flags": {},
            "label": "SHAREHOLDER",
            "points": [
                [
                    534,
                    456
                ],
                [
                    463,
                    450
                ],
                [
                    467,
                    439
                ],
                [
                    533,
                    442
                ]
            ],
            "shape_type": "polygon"
        },
        {
            "flags": {},
            "label": "SHAREHOLDER",
            "points": [
                [
                    502,
                    466
                ],
                [
                    463,
                    464
                ],
                [
                    463,
                    452
                ],
                [
                    502,
                    454
                ]
            ],
            "shape_type": "polygon"
        },
        {
            "flags": {},
            "label": "SHAREHOLDER",
            "points": [
                [
                    448,
                    450
                ],
                [
                    435,
                    447
                ],
                [
                    437,
                    437
                ],
                [
                    449,
                    441
                ]
            ],
            "shape_type": "polygon"
        },
        {
            "flags": {},
            "label": "SHAREHOLDER",
            "points": [
                [
                    461,
                    372
                ],
                [
                    449,
                    367
                ],
                [
                    451,
                    357
                ],
                [
                    464,
                    359
                ]
            ],
            "shape_type": "polygon"
        },
        {
            "flags": {},
            "label": "SHAREHOLDER",
            "points": [
                [
                    595,
                    460
                ],
                [
                    544,
                    458
                ],
                [
                    545,
                    443
                ],
                [
                    595,
                    448
                ]
            ],
            "shape_type": "polygon"
        },
        {
            "flags": {},
            "label": "SHAREHOLDER",
            "points": [
                [
                    605,
                    380
                ],
                [
                    553,
                    374
                ],
                [
                    551,
                    362
                ],
                [
                    606,
                    367
                ]
            ],
            "shape_type": "polygon"
        },
        {
            "flags": {},
            "label": "SHAREHOLDER",
            "points": [
                [
                    545,
                    387
                ],
                [
                    476,
                    384
                ],
                [
                    480,
                    371
                ],
                [
                    546,
                    374
                ]
            ],
            "shape_type": "polygon"
        },
        {
            "flags": {},
            "label": "SHAREHOLDER",
            "points": [
                [
                    536,
                    374
                ],
                [
                    478,
                    370
                ],
                [
                    478,
                    358
                ],
                [
                    535,
                    362
                ]
            ],
            "shape_type": "polygon"
        },
        {
            "flags": {},
            "label": "SHAREHOLDER",
            "points": [
                [
                    617,
                    866
                ],
                [
                    557,
                    862
                ],
                [
                    560,
                    848
                ],
                [
                    616,
                    852
                ]
            ],
            "shape_type": "polygon"
        },
        {
            "flags": {},
            "label": "SHAREHOLDER",
            "points": [
                [
                    638,
                    851
                ],
                [
                    558,
                    846
                ],
                [
                    560,
                    831
                ],
                [
                    638,
                    835
                ]
            ],
            "shape_type": "polygon"
        },
        {
            "flags": {},
            "label": "SHAREHOLDER",
            "points": [
                [
                    634,
                    835
                ],
                [
                    561,
                    832
                ],
                [
                    563,
                    817
                ],
                [
                    633,
                    822
                ]
            ],
            "shape_type": "polygon"
        },
        {
            "flags": {},
            "label": "SHAREHOLDER",
            "points": [
                [
                    632,
                    819
                ],
                [
                    561,
                    817
                ],
                [
                    561,
                    799
                ],
                [
                    632,
                    807
                ]
            ],
            "shape_type": "polygon"
        },
        {
            "flags": {},
            "label": "SHAREHOLDER",
            "points": [
                [
                    635,
                    806
                ],
                [
                    562,
                    798
                ],
                [
                    564,
                    783
                ],
                [
                    635,
                    791
                ]
            ],
            "shape_type": "polygon"
        },
        {
            "flags": {},
            "label": "SHAREHOLDER",
            "points": [
                [
                    640,
                    791
                ],
                [
                    564,
                    785
                ],
                [
                    567,
                    768
                ],
                [
                    640,
                    773
                ]
            ],
            "shape_type": "polygon"
        },
        {
            "flags": {},
            "label": "SHAREHOLDER",
            "points": [
                [
                    602,
                    770
                ],
                [
                    565,
                    769
                ],
                [
                    566,
                    756
                ],
                [
                    604,
                    758
                ]
            ],
            "shape_type": "polygon"
        },
        {
            "flags": {},
            "label": "SHAREHOLDER",
            "points": [
                [
                    638,
                    760
                ],
                [
                    566,
                    755
                ],
                [
                    569,
                    741
                ],
                [
                    638,
                    743
                ]
            ],
            "shape_type": "polygon"
        },
        {
            "flags": {},
            "label": "SHAREHOLDER",
            "points": [
                [
                    655,
                    745
                ],
                [
                    570,
                    740
                ],
                [
                    572,
                    725
                ],
                [
                    656,
                    731
                ]
            ],
            "shape_type": "polygon"
        },
        {
            "flags": {},
            "label": "SHAREHOLDER",
            "points": [
                [
                    644,
                    729
                ],
                [
                    574,
                    725
                ],
                [
                    574,
                    712
                ],
                [
                    643,
                    717
                ]
            ],
            "shape_type": "polygon"
        },
        {
            "flags": {},
            "label": "SHAREHOLDER",
            "points": [
                [
                    645,
                    715
                ],
                [
                    574,
                    712
                ],
                [
                    577,
                    698
                ],
                [
                    645,
                    700
                ]
            ],
            "shape_type": "polygon"
        },
        {
            "flags": {},
            "label": "SHAREHOLDER",
            "points": [
                [
                    622,
                    699
                ],
                [
                    576,
                    697
                ],
                [
                    575,
                    683
                ],
                [
                    620,
                    684
                ]
            ],
            "shape_type": "polygon"
        },
        {
            "flags": {},
            "label": "SHAREHOLDER",
            "points": [
                [
                    640,
                    685
                ],
                [
                    579,
                    681
                ],
                [
                    581,
                    668
                ],
                [
                    641,
                    672
                ]
            ],
            "shape_type": "polygon"
        },
        {
            "flags": {},
            "label": "SHAREHOLDER",
            "points": [
                [
                    636,
                    671
                ],
                [
                    581,
                    668
                ],
                [
                    582,
                    652
                ],
                [
                    637,
                    657
                ]
            ],
            "shape_type": "polygon"
        },
        {
            "flags": {},
            "label": "SHAREHOLDER",
            "points": [
                [
                    636,
                    655
                ],
                [
                    581,
                    653
                ],
                [
                    584,
                    639
                ],
                [
                    636,
                    644
                ]
            ],
            "shape_type": "polygon"
        },
        {
            "flags": {},
            "label": "SHAREHOLDER",
            "points": [
                [
                    662,
                    645
                ],
                [
                    581,
                    641
                ],
                [
                    583,
                    628
                ],
                [
                    666,
                    631
                ]
            ],
            "shape_type": "polygon"
        },
        {
            "flags": {},
            "label": "SHAREHOLDER",
            "points": [
                [
                    638,
                    630
                ],
                [
                    583,
                    626
                ],
                [
                    586,
                    613
                ],
                [
                    639,
                    616
                ]
            ],
            "shape_type": "polygon"
        },
        {
            "flags": {},
            "label": "SHAREHOLDER",
            "points": [
                [
                    657,
                    619
                ],
                [
                    586,
                    613
                ],
                [
                    589,
                    600
                ],
                [
                    660,
                    606
                ]
            ],
            "shape_type": "polygon"
        },
        {
            "flags": {},
            "label": "SHAREHOLDER",
            "points": [
                [
                    663,
                    605
                ],
                [
                    587,
                    600
                ],
                [
                    589,
                    585
                ],
                [
                    661,
                    591
                ]
            ],
            "shape_type": "polygon"
        },
        {
            "flags": {},
            "label": "SHAREHOLDER",
            "points": [
                [
                    660,
                    590
                ],
                [
                    589,
                    585
                ],
                [
                    590,
                    572
                ],
                [
                    659,
                    579
                ]
            ],
            "shape_type": "polygon"
        },
        {
            "flags": {},
            "label": "SHAREHOLDER",
            "points": [
                [
                    645,
                    576
                ],
                [
                    589,
                    573
                ],
                [
                    591,
                    561
                ],
                [
                    644,
                    565
                ]
            ],
            "shape_type": "polygon"
        },
        {
            "flags": {},
            "label": "SHAREHOLDER",
            "points": [
                [
                    663,
                    565
                ],
                [
                    591,
                    561
                ],
                [
                    594,
                    547
                ],
                [
                    664,
                    551
                ]
            ],
            "shape_type": "polygon"
        },
        {
            "flags": {},
            "label": "SHAREHOLDER",
            "points": [
                [
                    647,
                    550
                ],
                [
                    592,
                    547
                ],
                [
                    596,
                    535
                ],
                [
                    647,
                    539
                ]
            ],
            "shape_type": "polygon"
        },
        {
            "flags": {},
            "label": "SHAREHOLDER",
            "points": [
                [
                    662,
                    541
                ],
                [
                    595,
                    535
                ],
                [
                    596,
                    522
                ],
                [
                    663,
                    527
                ]
            ],
            "shape_type": "polygon"
        },
        {
            "flags": {},
            "label": "SHAREHOLDER",
            "points": [
                [
                    661,
                    527
                ],
                [
                    594,
                    520
                ],
                [
                    594,
                    518
                ],
                [
                    598,
                    509
                ],
                [
                    662,
                    514
                ]
            ],
            "shape_type": "polygon"
        },
        {
            "flags": {},
            "label": "SHAREHOLDER",
            "points": [
                [
                    628,
                    510
                ],
                [
                    597,
                    510
                ],
                [
                    597,
                    498
                ],
                [
                    629,
                    499
                ]
            ],
            "shape_type": "polygon"
        },
        {
            "flags": {},
            "label": "SHAREHOLDER",
            "points": [
                [
                    657,
                    503
                ],
                [
                    598,
                    497
                ],
                [
                    599,
                    486
                ],
                [
                    659,
                    490
                ]
            ],
            "shape_type": "polygon"
        },
        {
            "flags": {},
            "label": "SHAREHOLDER",
            "points": [
                [
                    668,
                    492
                ],
                [
                    600,
                    486
                ],
                [
                    602,
                    473
                ],
                [
                    670,
                    479
                ]
            ],
            "shape_type": "polygon"
        },
        {
            "flags": {},
            "label": "SHAREHOLDER",
            "points": [
                [
                    662,
                    478
                ],
                [
                    602,
                    473
                ],
                [
                    604,
                    461
                ],
                [
                    663,
                    466
                ]
            ],
            "shape_type": "polygon"
        },
        {
            "flags": {},
            "label": "SHAREHOLDER",
            "points": [
                [
                    665,
                    465
                ],
                [
                    603,
                    461
                ],
                [
                    604,
                    448
                ],
                [
                    665,
                    452
                ]
            ],
            "shape_type": "polygon"
        },
        {
            "flags": {},
            "label": "SHAREHOLDER",
            "points": [
                [
                    629,
                    450
                ],
                [
                    604,
                    449
                ],
                [
                    605,
                    437
                ],
                [
                    631,
                    441
                ]
            ],
            "shape_type": "polygon"
        },
        {
            "flags": {},
            "label": "SHAREHOLDER",
            "points": [
                [
                    677,
                    444
                ],
                [
                    605,
                    438
                ],
                [
                    608,
                    426
                ],
                [
                    677,
                    430
                ]
            ],
            "shape_type": "polygon"
        },
        {
            "flags": {},
            "label": "SHAREHOLDER",
            "points": [
                [
                    662,
                    429
                ],
                [
                    606,
                    424
                ],
                [
                    606,
                    414
                ],
                [
                    662,
                    419
                ]
            ],
            "shape_type": "polygon"
        },
        {
            "flags": {},
            "label": "SHAREHOLDER",
            "points": [
                [
                    672,
                    420
                ],
                [
                    608,
                    414
                ],
                [
                    610,
                    403
                ],
                [
                    676,
                    408
                ]
            ],
            "shape_type": "polygon"
        },
        {
            "flags": {},
            "label": "SHAREHOLDER",
            "points": [
                [
                    677,
                    408
                ],
                [
                    608,
                    402
                ],
                [
                    609,
                    391
                ],
                [
                    679,
                    396
                ]
            ],
            "shape_type": "polygon"
        },
        {
            "flags": {},
            "label": "SHAREHOLDER",
            "points": [
                [
                    660,
                    393
                ],
                [
                    611,
                    390
                ],
                [
                    610,
                    381
                ],
                [
                    660,
                    383
                ]
            ],
            "shape_type": "polygon"
        },
        {
            "flags": {},
            "label": "SHAREHOLDER",
            "points": [
                [
                    673,
                    384
                ],
                [
                    611,
                    380
                ],
                [
                    611,
                    369
                ],
                [
                    672,
                    373
                ]
            ],
            "shape_type": "polygon"
        },
        {
            "flags": {},
            "label": "SHAREHOLDER",
            "points": [
                [
                    643,
                    370
                ],
                [
                    613,
                    368
                ],
                [
                    615,
                    359
                ],
                [
                    645,
                    360
                ]
            ],
            "shape_type": "polygon"
        },
        {
            "flags": {},
            "label": "SHAREHOLDER",
            "points": [
                [
                    672,
                    360
                ],
                [
                    612,
                    358
                ],
                [
                    614,
                    346
                ],
                [
                    677,
                    351
                ]
            ],
            "shape_type": "polygon"
        },
        {
            "flags": {},
            "label": "DOCUMENT",
            "points": [
                [
                    897,
                    1016
                ],
                [
                    276,
                    965
                ],
                [
                    430,
                    247
                ],
                [
                    591,
                    260
                ],
                [
                    854,
                    270
                ],
                [
                    897,
                    335
                ],
                [
                    900,
                    745
                ]
            ],
            "shape_type": "polygon"
        }
    ],
    "version": "5.0.1"
}